pypi_latest/__init__.py
pypi_latest/__main__.py
pypi_latest/py.typed
pypi_latest/questionary.py
pypi_latest-0.1.2.dist-info/entry_points.txt
pypi_latest-0.1.2.dist-info/LICENSE
pypi_latest-0.1.2.dist-info/WHEEL
pypi_latest-0.1.2.dist-info/METADATA
pypi_latest-0.1.2.dist-info/RECORD
