Metadata-Version: 2.1
Name: pypi-latest
Version: 0.1.2
Summary: Verify that currently installed version is the latest one released on PyPI and update it if not.
Home-page: https://github.com/cookiejar/pypi-latest
License: Apache2.0
Author: Lukas Heumos
Author-email: lukas.heumos@posteo.net
Requires-Python: >=3.6.1,<4
Classifier: License :: Other/Proprietary License
Classifier: Programming Language :: Python :: 3
Classifier: Programming Language :: Python :: 3.10
Classifier: Programming Language :: Python :: 3.7
Classifier: Programming Language :: Python :: 3.8
Classifier: Programming Language :: Python :: 3.9
Requires-Dist: PyYAML (>=5.4.1)
Requires-Dist: click (>=7.0.0)
Requires-Dist: questionary (>=1.9.0)
Requires-Dist: rich (>=10.4.0)
Project-URL: Documentation, https://pypi-latest.readthedocs.io
Project-URL: Repository, https://github.com/cookiejar/pypi-latest
